pyhindsight/__init__.py
pyhindsight/analysis.py
pyhindsight/utils.py
pyhindsight/browsers/__init__.py
pyhindsight/browsers/brave.py
pyhindsight/browsers/chrome.py
pyhindsight/browsers/webbrowser.py
pyhindsight/lib/site_data_pb2.py
pyhindsight/lib/buf/__init__.py
pyhindsight/lib/buf/components/__init__.py
pyhindsight/lib/buf/components/sync/__init__.py
pyhindsight/lib/buf/components/sync/protocol/__init__.py
pyhindsight/lib/buf/components/sync/protocol/app_list_specifics_pb2.py
pyhindsight/lib/buf/components/sync/protocol/app_setting_specifics_pb2.py
pyhindsight/lib/buf/components/sync/protocol/app_specifics_pb2.py
pyhindsight/lib/buf/components/sync/protocol/arc_package_specifics_pb2.py
pyhindsight/lib/buf/components/sync/protocol/autofill_offer_specifics_pb2.py
pyhindsight/lib/buf/components/sync/protocol/autofill_specifics_pb2.py
pyhindsight/lib/buf/components/sync/protocol/autofill_valuable_setting_specifics_pb2.py
pyhindsight/lib/buf/components/sync/protocol/autofill_valuable_specifics_pb2.py
pyhindsight/lib/buf/components/sync/protocol/autofill_wallet_credential_specifics_pb2.py
pyhindsight/lib/buf/components/sync/protocol/autofill_wallet_usage_specifics_pb2.py
pyhindsight/lib/buf/components/sync/protocol/bookmark_model_metadata_pb2.py
pyhindsight/lib/buf/components/sync/protocol/bookmark_specifics_pb2.py
pyhindsight/lib/buf/components/sync/protocol/client_commands_pb2.py
pyhindsight/lib/buf/components/sync/protocol/client_debug_info_pb2.py
pyhindsight/lib/buf/components/sync/protocol/collaboration_group_metadata_pb2.py
pyhindsight/lib/buf/components/sync/protocol/collaboration_group_specifics_pb2.py
pyhindsight/lib/buf/components/sync/protocol/contact_info_specifics_pb2.py
pyhindsight/lib/buf/components/sync/protocol/cookie_specifics_pb2.py
pyhindsight/lib/buf/components/sync/protocol/data_type_progress_marker_pb2.py
pyhindsight/lib/buf/components/sync/protocol/data_type_state_pb2.py
pyhindsight-20260130.dist-info/licenses/LICENSE.md
pyhindsight-20260130.dist-info/METADATA
pyhindsight-20260130.dist-info/WHEEL
pyhindsight-20260130.dist-info/top_level.txt
pyhindsight-20260130.dist-info/RECORD
