Metadata-Version: 2.4
Name: pyhindsight
Version: 20260130
Summary: Browser forensics for Google Chrome/Chromium
Home-page: https://github.com/obsidianforensics/hindsight
Author: Ryan Benson
Author-email: ryan@hindsig.ht
License: Apache
Keywords: chrome,forensics,dfir,google-chrome,chromium
Classifier: Development Status :: 5 - Production/Stable
Classifier: License :: OSI Approved :: Apache Software License
Classifier: Topic :: Security
Classifier: Topic :: System :: Recovery Tools
Requires-Python: >=3.9
License-File: LICENSE.md
Requires-Dist: bottle>=0.12.18
Requires-Dist: keyring>=21.2.1
Requires-Dist: pycryptodomex>=3.9.7
Requires-Dist: pytz>=2021.3
Requires-Dist: xlsxwriter>=3.1
Requires-Dist: puremagic>=1.11
Requires-Dist: protobuf>=4.23
Requires-Dist: rich>=13.0
Dynamic: author
Dynamic: author-email
Dynamic: classifier
Dynamic: home-page
Dynamic: keywords
Dynamic: license
Dynamic: license-file
Dynamic: requires-dist
Dynamic: requires-python
Dynamic: summary
